Workbook

Sheet 📊 Dashboard
B1: 📈 INVESTOR PORTFOLIO COMMAND CENTER
B2: Report Date: 18 April 2026 | Update your data in each sheet tab below
B3: KEY PORTFOLIO METRICS
B4: 💰 Total Portfolio Value | D4: 📈 Total Invested | F4: 💹 Overall P&L | H4: 📊 Overall P&L % | J4: 🎯 GTT Orders Active | L4: 🔄 Swing Trades Open
B5: =SUM('📋 Portfolio'!H2:H21) -> 0 | D5: =SUM('📋 Portfolio'!G2:G21) -> 15185 | F5: =SUM('📋 Portfolio'!I2:I21) -> 1835000 | H5: =(SUM('📋 Portfolio'!H2:H21)-SUM('📋 Portfolio'!G2:G21))/IF(SUM('📋 Portfolio'!G2:G21)=0,1,SUM('📋 Portfolio'!G2:G21)) -> -1 | J5: =COUNTA('🎯 GTT Plan'!B2:B21) -> 17 | L5: =COUNTA('🔄 Swing Trading'!B2:B16) -> 14
B8: 📋 PORTFOLIO SNAPSHOT | H8: 💡 TOP BUY SUGGESTIONS TODAY
B9: Stock | C9: Qty | D9: Avg Cost | E9: CMP | F9: Current Value | G9: P&L | H9: Stock | I9: Rating | J9: Target | K9: Upside%
B10: RELIANCE | C10: 50 | D10: 2400.00 | E10: 2520.00 | F10: =C10*D10 -> 120000 | G10: =F10-(C10*E10) -> -6000 | H10: HCLTECH | I10: ⭐⭐⭐⭐⭐ | J10: 1400 | K10: 18%
B11: INFY | C11: 100 | D11: 1500.00 | E11: 1620.00 | F11: =C11*D11 -> 150000 | G11: =F11-(C11*E11) -> -12000 | H11: SUNPHARMA | I11: ⭐⭐⭐⭐ | J11: 1050 | K11: 12%
B12: TCS | C12: 25 | D12: 3400.00 | E12: 3600.00 | F12: =C12*D12 -> 85000 | G12: =F12-(C12*E12) -> -5000 | H12: POWERGRID | I12: ⭐⭐⭐⭐ | J12: 280 | K12: 15%
B13: HDFCBANK | C13: 75 | D13: 1650.00 | E13: 1580.00 | F13: =C13*D13 -> 123750 | G13: =F13-(C13*E13) -> 5250 | H13: COALINDIA | I13: ⭐⭐⭐ | J13: 270 | K13: 10%
B14: WIPRO | C14: 200 | D14: 450.00 | E14: 430.00 | F14: =C14*D14 -> 90000 | G14: =F14-(C14*E14) -> 4000 | H14: LT | I14: ⭐⭐⭐⭐⭐ | J14: 3800 | K14: 20%
B16: 🔁 BUYBACK OPPORTUNITIES | H16: 🎯 ACTIVE GTT ORDERS
B17: Company | C17: Buyback Price | D17: CMP | E17: Premium% | F17: Status | H17: Stock | I17: Trigger | J17: Type | K17: Status
B18: INFY | C18: ₹1,800 | D18: ₹1,620 | E18: 11.1% | F18: 🟢 Open | H18: RELIANCE | I18: 2300 | J18: Buy on dip | K18: 🟢 Active
B19: TCS | C19: ₹4,200 | D19: ₹3,600 | E19: 16.7% | F19: 🟢 Open | H19: INFY | I19: 1550 | J19: Stop Loss | K19: 🟡 Pending
B20: HCL TECH | C20: ₹1,500 | D20: ₹1,185 | E20: 26.6% | F20: 🟡 Expected | H20: HDFCBANK | I20: 1500 | J20: Buy Target | K20: 🟢 Active
B21: WIPRO | C21: ₹500 | D21: ₹430 | E21: 16.3% | F21: 🟢 Open | H21: TCS | I21: 3300 | J21: Profit Book | K21: 🔵 Set
B22: 🔄 SWING TRADE WATCHLIST
B23: Stock | C23: Setup | D23: Entry Zone | E23: Target | F23: Stop Loss | G23: Reward:Risk | H23: Days | I23: Confidence | J23: Action
B24: INFY | C24: Buyback+Dip | D24: 1600-1650 | E24: 1780 | F24: 1550 | G24: 3.6:1 | H24: 5-8 | I24: 🔥 High | J24: BUY
B25: WIPRO | C25: Buyback Rally | D25: 425-435 | E25: 490 | F25: 410 | G25: 2.8:1 | H25: 7-10 | I25: 🔥 High | J25: BUY
B26: TCS | C26: Value+Buyback | D26: 3550-3650 | E26: 3900 | F26: 3450 | G26: 2.5:1 | H26: 10-15 | I26: ✅ Med | J26: WATCH
B27: HCL TECH | C27: Pre-Buyback | D27: 1150-1200 | E27: 1380 | F27: 1100 | G27: 3.2:1 | H27: 8-12 | I27: 🔥 High | J27: BUY

Sheet 📋 Portfolio
B1: 📋 MY INVESTMENT PORTFOLIO
B2: Stock / Company | C2: Sector | D2: Exchange | E2: Buy Date | F2: Qty | G2: Avg Buy Price (₹) | H2: CMP (₹) [INPUT] | I2: Total Invested (₹) | J2: Current Value (₹) | K2: P&L (₹) | L2: P&L % | M2: Weight % | N2: 52W High | O2: 52W Low
B3: RELIANCE | C3: Energy | D3: NSE | E3: 01-Jan-2024 | F3: 50 | G3: 2400 | H3: 0 | I3: =F3*G3 -> 120000 | J3: =F3*H3 -> 0 | K3: =J3-I3 -> -120000 | L3: =IF(I3=0,0,(J3-I3)/I3) -> -1 | M3: =IF(SUM(J$3:J$22)=0,0,J3/SUM(J$3:J$22)) -> 0 | N3: 2800 | O3: 2100
B4: INFY | C4: IT | D4: NSE | E4: 15-Feb-2024 | F4: 100 | G4: 1500 | H4: 0 | I4: =F4*G4 -> 150000 | J4: =F4*H4 -> 0 | K4: =J4-I4 -> -150000 | L4: =IF(I4=0,0,(J4-I4)/I4) -> -1 | M4: =IF(SUM(J$3:J$22)=0,0,J4/SUM(J$3:J$22)) -> 0 | N4: 1900 | O4: 1350
B5: TCS | C5: IT | D5: NSE | E5: 10-Mar-2024 | F5: 25 | G5: 3400 | H5: 0 | I5: =F5*G5 -> 85000 | J5: =F5*H5 -> 0 | K5: =J5-I5 -> -85000 | L5: =IF(I5=0,0,(J5-I5)/I5) -> -1 | M5: =IF(SUM(J$3:J$22)=0,0,J5/SUM(J$3:J$22)) -> 0 | N5: 4000 | O5: 3100
B6: HDFCBANK | C6: Banking | D6: NSE | E6: 05-Apr-2024 | F6: 75 | G6: 1650 | H6: 0 | I6: =F6*G6 -> 123750 | J6: =F6*H6 -> 0 | K6: =J6-I6 -> -123750 | L6: =IF(I6=0,0,(J6-I6)/I6) -> -1 | M6: =IF(SUM(J$3:J$22)=0,0,J6/SUM(J$3:J$22)) -> 0 | N6: 1900 | O6: 1400
B7: WIPRO | C7: IT | D7: NSE | E7: 20-May-2024 | F7: 200 | G7: 450 | H7: 0 | I7: =F7*G7 -> 90000 | J7: =F7*H7 -> 0 | K7: =J7-I7 -> -90000 | L7: =IF(I7=0,0,(J7-I7)/I7) -> -1 | M7: =IF(SUM(J$3:J$22)=0,0,J7/SUM(J$3:J$22)) -> 0 | N7: 570 | O7: 380
B8: SUNPHARMA | C8: Pharma | D8: NSE | E8: 01-Jun-2024 | F8: 80 | G8: 900 | H8: 0 | I8: =F8*G8 -> 72000 | J8: =F8*H8 -> 0 | K8: =J8-I8 -> -72000 | L8: =IF(I8=0,0,(J8-I8)/I8) -> -1 | M8: =IF(SUM(J$3:J$22)=0,0,J8/SUM(J$3:J$22)) -> 0 | N8: 1100 | O8: 780
B9: HCLTECH | C9: IT | D9: NSE | E9: 15-Jul-2024 | F9: 60 | G9: 1200 | H9: 0 | I9: =F9*G9 -> 72000 | J9: =F9*H9 -> 0 | K9: =J9-I9 -> -72000 | L9: =IF(I9=0,0,(J9-I9)/I9) -> -1 | M9: =IF(SUM(J$3:J$22)=0,0,J9/SUM(J$3:J$22)) -> 0 | N9: 1500 | O9: 1050
B10: POWERGRID | C10: Utilities | D10: NSE | E10: 01-Aug-2024 | F10: 300 | G10: 240 | H10: 0 | I10: =F10*G10 -> 72000 | J10: =F10*H10 -> 0 | K10: =J10-I10 -> -72000 | L10: =IF(I10=0,0,(J10-I10)/I10) -> -1 | M10: =IF(SUM(J$3:J$22)=0,0,J10/SUM(J$3:J$22)) -> 0 | N10: 310 | O10: 200
B11: COALINDIA | C11: Mining | D11: NSE | E11: 10-Sep-2024 | F11: 150 | G11: 245 | H11: 0 | I11: =F11*G11 -> 36750 | J11: =F11*H11 -> 0 | K11: =J11-I11 -> -36750 | L11: =IF(I11=0,0,(J11-I11)/I11) -> -1 | M11: =IF(SUM(J$3:J$22)=0,0,J11/SUM(J$3:J$22)) -> 0 | N11: 295 | O11: 210
B12: LT | C12: Infra | D12: NSE | E12: 15-Oct-2024 | F12: 30 | G12: 3200 | H12: 0 | I12: =F12*G12 -> 96000 | J12: =F12*H12 -> 0 | K12: =J12-I12 -> -96000 | L12: =IF(I12=0,0,(J12-I12)/I12) -> -1 | M12: =IF(SUM(J$3:J$22)=0,0,J12/SUM(J$3:J$22)) -> 0 | N12: 3900 | O12: 2800
B13: 📊 TOTAL | I13: =SUM(I3:I12) -> 917500 | J13: =SUM(J3:J12) -> 0 | K13: =SUM(K3:K12) -> -917500 | L13: =IF(I13=0,0,(J13-I13)/I13) -> -1
B15: 📝 NOTE: Blue cells = User Input. Yellow highlighted cell = CMP (enter today's price). All calculations auto-update.

Sheet 💡 Buy Suggestions
B1: 💡 BUY SUGGESTIONS — FUNDAMENTAL & TECHNICAL ANALYSIS
B2: ⭐⭐⭐⭐⭐ = Strong Buy | ⭐⭐⭐⭐ = Buy | ⭐⭐⭐ = Accumulate | 🔴 = Avoid/Wait
B3: Company | C3: Sector | D3: CMP (₹) | E3: Buy Zone | F3: Target 1 | G3: Target 2 | H3: Stop Loss | I3: Upside % | J3: P/E Ratio | K3: EPS Growth % | L3: D/E Ratio | M3: Rating | N3: Key Reason
B4: HCLTECH | C4: IT | D4: 1185 | E4: 1150-1200 | F4: 1380 | G4: 1500 | H4: 1080 | I4: 18-26% | J4: 22 | K4: 15% | L4: 0.1 | M4: ⭐⭐⭐⭐⭐ | N4: Buyback + Strong Q Results + IT Demand
B5: SUNPHARMA | C5: Pharma | D5: 925 | E5: 900-950 | F5: 1050 | G5: 1200 | H5: 850 | I5: 14-30% | J5: 28 | K5: 18% | L5: 0.2 | M5: ⭐⭐⭐⭐ | N5: US Generic Recovery + R&D Pipeline
B6: POWERGRID | C6: Utilities | D6: 240 | E6: 235-245 | F6: 280 | G6: 310 | H6: 215 | I6: 17-29% | J6: 18 | K6: 12% | L6: 1.8 | M6: ⭐⭐⭐⭐ | N6: Govt Capex + Dividend Yield 5.2%
B7: COALINDIA | C7: Mining | D7: 245 | E7: 238-250 | F7: 270 | G7: 295 | H7: 220 | I7: 10-20% | J7: 7 | K7: 8% | L7: 0.0 | M7: ⭐⭐⭐⭐ | N7: Near-Zero Debt + 8% Dividend Yield
B8: LT | C8: Infra | D8: 3200 | E8: 3100-3300 | F8: 3800 | G8: 4200 | H8: 2900 | I8: 19-31% | J8: 32 | K8: 20% | L8: 1.5 | M8: ⭐⭐⭐⭐⭐ | N8: Order Book +25% YoY + Govt Projects
B9: RELIANCE | C9: Energy | D9: 2520 | E9: 2400-2550 | F9: 2900 | G9: 3200 | H9: 2250 | I9: 15-27% | J9: 26 | K9: 14% | L9: 0.4 | M9: ⭐⭐⭐⭐ | N9: Jio + Retail + O2C Diversification
B10: AXISBANK | C10: Banking | D10: 1050 | E10: 1020-1070 | F10: 1220 | G10: 1350 | H10: 970 | I10: 16-29% | J10: 14 | K10: 22% | L10: 0.8 | M10: ⭐⭐⭐⭐ | N10: NIM Expansion + Low NPA Trend
B11: BAJFINANCE | C11: NBFC | D11: 6800 | E11: 6600-7000 | F11: 7800 | G11: 8500 | H11: 6200 | I11: 15-25% | J11: 30 | K11: 28% | L11: 3.2 | M11: ⭐⭐⭐⭐ | N11: AUM Growth + New Products
B12: TITAN | C12: Consumer | D12: 3200 | E12: 3100-3300 | F12: 3700 | G12: 4000 | H12: 2950 | I12: 16-25% | J12: 72 | K12: 20% | L12: 0.1 | M12: ⭐⭐⭐ | N12: Jewellery + Watches Market Leader
B13: NTPC | C13: Energy | D13: 350 | E13: 340-360 | F13: 410 | G13: 450 | H13: 320 | I13: 17-29% | J13: 15 | K13: 10% | L13: 2.0 | M13: ⭐⭐⭐⭐ | N13: Green Energy Expansion + Dividend
B15: KEY ANALYSIS POINTS — WHAT TO CHECK BEFORE BUYING
B16: 1️⃣ Fundamentals | C16: P/E < Sector Average | EPS Growth > 15% | Debt/Equity < 1 | ROE > 15% | Strong Cash Flow
B17: 2️⃣ Technicals | C17: Price above 200 DMA | RSI 40–60 (not overbought) | MACD Crossover | Volume spike on buy
B18: 3️⃣ Valuation | C18: Check P/B Ratio vs Peers | Dividend Yield > 2% is bonus | Compare EV/EBITDA
B19: 4️⃣ Catalysts | C19: Upcoming earnings | Buyback announcement | New product/order | Sector tailwind
B20: 5️⃣ Risk Check | C20: Promoter Pledge < 10% | No major litigation | No auditor concern | FII/DII trend positive
B21: 6️⃣ Entry Strategy | C21: Buy in 2–3 tranches | First buy at lower zone | Average on 5% dip | Set GTT immediately
B22: 7️⃣ Exit Plan | C22: Book 50% at Target 1 | Let rest run to Target 2 | Trail stop loss | Never average loss

Sheet 🔁 Buyback Opps
B1: 🔁 SHARE BUYBACK OPPORTUNITIES — DEEP VALUE TRACKER
B2: 💡 WHAT IS A BUYBACK? Company repurchases its own shares → reduces supply → EPS increases → Share price rises
B3: Company | C3: CMP (₹) | D3: Buyback Price (₹) | E3: Premium to CMP% | F3: Buyback Size (₹Cr) | G3: Acceptance Ratio% | H3: Record Date | I3: Status | J3: Expected Gain% | K3: Action Needed
B4: INFOSYS | C4: 1620 | D4: 1800 | E4: =((D4-C4)/C4) -> 0.11111111 | F4: 9300 | G4: 25% | H4: 15-Jun-2025 | I4: 🟢 OPEN | J4: =((D4-C4)/C4) -> 0.11111111 | K4: TENDER NOW
B5: TCS | C5: 3600 | D5: 4200 | E5: =((D5-C5)/C5) -> 0.16666667 | F5: 17000 | G5: 15% | H5: 30-Jun-2025 | I5: 🟢 OPEN | J5: =((D5-C5)/C5) -> 0.16666667 | K5: TENDER NOW
B6: WIPRO | C6: 430 | D6: 500 | E6: =((D6-C6)/C6) -> 0.1627907 | F6: 2500 | G6: 30% | H6: 15-Jul-2025 | I6: 🟢 OPEN | J6: =((D6-C6)/C6) -> 0.1627907 | K6: TENDER NOW
B7: HCL TECH | C7: 1185 | D7: 1500 | E7: =((D7-C7)/C7) -> 0.26582278 | F7: 4500 | G7: 20% | H7: 31-Aug-2025 | I7: 🟡 EXPECTED | J7: =((D7-C7)/C7) -> 0.26582278 | K7: ACCUMULATE
B8: MPHASIS | C8: 2100 | D8: 2600 | E8: =((D8-C8)/C8) -> 0.23809524 | F8: 1200 | G8: 35% | H8: 30-Sep-2025 | I8: 🟡 EXPECTED | J8: =((D8-C8)/C8) -> 0.23809524 | K8: WATCH
B10: 📚 BUYBACK ARBITRAGE — HOW IT WORKS (Step by Step)
B11: STEP 1: Identify | C11: Company announces buyback at PREMIUM to current market price (CMP). Example: CMP=₹1620, Buyback=₹1800
B12: STEP 2: Calculate | C12: Premium % = (Buyback Price - CMP)/CMP × 100. Here: (1800-1620)/1620 × 100 = 11.1% above market
B13: STEP 3: Buy Shares | C13: Buy shares in open market BEFORE record date. More shares = more tender opportunity
B14: STEP 4: Tender Shares | C14: Submit shares in buyback tender offer via your broker before deadline
B15: STEP 5: Acceptance | C15: Company accepts based on ratio. E.g., 25% ratio = 25 shares accepted out of 100 tendered
B16: STEP 6: Profit | C16: Accepted shares sold at buyback price (₹1800) vs cost (₹1620) = ₹180/share profit
B17: STEP 7: Unaccepted | C17: Remaining shares stay in your demat. Continue holding or sell in market
B18: ⚠️ Risk Note | C18: Acceptance ratio may be low. Price may fall post-buyback. Tax: 20% STCG if held <12 months

Sheet 🎯 GTT Plan
B1: 🎯 GTT (GOOD TILL TRIGGERED) ORDER PLANNER
B2: 💡 GTT = Set it and Forget it! Triggers automatically when price hits your level. Available on Zerodha Kite, Groww, Upstox, Angel One
D3: 🟢 GTT BUY | G3: 🔴 GTT SELL / STOP | J3: 🔵 GTT PROFIT BOOK
D4: Triggers a BUY when price FALLS to your target entry. Perfect for buying dips automatically. | G4: Triggers a SELL when price FALLS below stop loss. Protects capital automatically. | J4: Triggers a SELL when price RISES to target. Lock in profits without monitoring.
B5: Stock | C5: CMP (₹) | D5: GTT Type | E5: Trigger Price (₹) | F5: Qty | G5: Order Value (₹) | H5: Stop Loss | I5: Target | J5: R:R Ratio | K5: Broker | L5: Notes / Status
B6: RELIANCE | C6: 2520 | D6: 🟢 GTT BUY | E6: 2300 | F6: 25 | G6: =E6*F6 -> 57500 | H6: 2150 | I6: 2800 | J6: =IF((E6-H6)=0,0,ROUND((I6-E6)/(E6-H6),1)) -> 3.3 | K6: Zerodha Kite | L6: Buy on 8.7% dip — strong support
B7: INFY | C7: 1620 | D7: 🔴 GTT STOP LOSS | E7: 1530 | F7: 100 | G7: =E7*F7 -> 153000 | H7: 1530 | I7: 1850 | J7: =IF((E7-H7)=0,0,ROUND((I7-E7)/(E7-H7),1)) -> 0 | K7: Groww | L7: Protect 5.5% downside
B8: TCS | C8: 3600 | D8: 🔵 GTT PROFIT BOOK | E8: 3900 | F8: 25 | G8: =E8*F8 -> 97500 | H8: 3300 | I8: 3900 | J8: =IF((E8-H8)=0,0,ROUND((I8-E8)/(E8-H8),1)) -> 0 | K8: Zerodha Kite | L8: Book at ₹3900 resistance
B9: HDFCBANK | C9: 1580 | D9: 🟢 GTT BUY | E9: 1480 | F9: 50 | G9: =E9*F9 -> 74000 | H9: 1380 | I9: 1800 | J9: =IF((E9-H9)=0,0,ROUND((I9-E9)/(E9-H9),1)) -> 3.2 | K9: Upstox | L9: Buy at 52W support zone
B10: WIPRO | C10: 430 | D10: 🟢 GTT BUY | E10: 400 | F10: 200 | G10: =E10*F10 -> 80000 | H10: 375 | I10: 500 | J10: =IF((E10-H10)=0,0,ROUND((I10-E10)/(E10-H10),1)) -> 4 | K10: Angel One | L10: Pre-buyback accumulation
B11: HCLTECH | C11: 1185 | D11: 🟢 GTT BUY | E11: 1120 | F11: 60 | G11: =E11*F11 -> 67200 | H11: 1050 | I11: 1400 | J11: =IF((E11-H11)=0,0,ROUND((I11-E11)/(E11-H11),1)) -> 4 | K11: Zerodha Kite | L11: Buyback expected — buy dip
B12: COALINDIA | C12: 245 | D12: 🟢 GTT BUY | E12: 225 | F12: 300 | G12: =E12*F12 -> 67500 | H12: 210 | I12: 275 | J12: =IF((E12-H12)=0,0,ROUND((I12-E12)/(E12-H12),1)) -> 3.3 | K12: Groww | L12: High dividend yield stock
B13: SUNPHARMA | C13: 925 | D13: 🔵 GTT PROFIT BOOK | E13: 1050 | F13: 80 | G13: =E13*F13 -> 84000 | H13: 850 | I13: 1050 | J13: =IF((E13-H13)=0,0,ROUND((I13-E13)/(E13-H13),1)) -> 0 | K13: Zerodha Kite | L13: Exit at target — 13.5% profit
B15: 📋 GTT RULES & BEST PRACTICES
B16: ✅ Always set GTT immediately after buying — don't rely on memory to set stop loss
B17: ✅ For every ₹1 risk (stop loss), ensure at least ₹2 reward (target) — minimum 1:2 R:R ratio
B18: ✅ GTT Buy Orders: Place at strong support levels, 200 DMA, or buyback accumulation zones
B19: ✅ GTT Sell Orders: Place stop at recent swing low — never more than 7-8% below entry
B20: ✅ GTT Profit Book: Place first target at resistance; let remaining run with trailing stop
B21: ⚠️ GTT orders expire after 1 year on most brokers — renew them periodically
B22: ⚠️ GTT does not guarantee execution at exact price in fast-moving markets (gap risk)
B23: 💡 TWO-LEG GTT: Set both stop loss AND target simultaneously for full automation

Sheet 🔄 Swing Trading
B1: 🔄 SWING TRADING — BUYBACK & DEEP VALUE OPPORTUNITIES
B2: Strategy: Buy deep-value stocks near buyback price support | Hold 5-15 days | Target 8-15% move | Set GTT stop immediately
B3: Stock | C3: Setup Type | D3: Entry Zone (₹) | E3: Target 1 (₹) | F3: Target 2 (₹) | G3: Stop Loss (₹) | H3: Holding Days | I3: R:R Ratio | J3: Confidence | K3: Capital (₹) | L3: P&L If T1 Hit (₹) | M3: P&L If T2 Hit (₹) | N3: Status
B4: INFY | C4: Buyback + Dip | D4: 1600 | E4: 1720 | F4: 1780 | G4: 1550 | H4: 5-8 | I4: =IFERROR(ROUND((E4-D4)/(D4-G4),1),0) -> 2.4 | J4: 🔥 HIGH | K4: 50000 | L4: =IFERROR(ROUND((E4-D4)/D4*K4,0),0) -> 3750 | M4: =IFERROR(ROUND((F4-D4)/D4*K4,0),0) -> 5625 | N4: 🟢 ACTIVE
B5: WIPRO | C5: Pre-Buyback | D5: 425 | E5: 470 | F5: 495 | G5: 405 | H5: 7-10 | I5: =IFERROR(ROUND((E5-D5)/(D5-G5),1),0) -> 2.3 | J5: 🔥 HIGH | K5: 40000 | L5: =IFERROR(ROUND((E5-D5)/D5*K5,0),0) -> 4235 | M5: =IFERROR(ROUND((F5-D5)/D5*K5,0),0) -> 6588 | N5: 🟢 ACTIVE
B6: HCL TECH | C6: Buyback Play | D6: 1150 | E6: 1300 | F6: 1380 | G6: 1100 | H6: 8-12 | I6: =IFERROR(ROUND((E6-D6)/(D6-G6),1),0) -> 3 | J6: 🔥 HIGH | K6: 60000 | L6: =IFERROR(ROUND((E6-D6)/D6*K6,0),0) -> 7826 | M6: =IFERROR(ROUND((F6-D6)/D6*K6,0),0) -> 12000 | N6: 🟡 WATCH
B7: TCS | C7: Value Rebound | D7: 3550 | E7: 3800 | F7: 3900 | G7: 3400 | H7: 10-15 | I7: =IFERROR(ROUND((E7-D7)/(D7-G7),1),0) -> 1.7 | J7: ✅ MED | K7: 80000 | L7: =IFERROR(ROUND((E7-D7)/D7*K7,0),0) -> 5634 | M7: =IFERROR(ROUND((F7-D7)/D7*K7,0),0) -> 7887 | N7: 🟡 WATCH
B8: MPHASIS | C8: Deep Value | D8: 2050 | E8: 2300 | F8: 2500 | G8: 1950 | H8: 10-14 | I8: =IFERROR(ROUND((E8-D8)/(D8-G8),1),0) -> 2.5 | J8: ✅ MED | K8: 50000 | L8: =IFERROR(ROUND((E8-D8)/D8*K8,0),0) -> 6098 | M8: =IFERROR(ROUND((F8-D8)/D8*K8,0),0) -> 10976 | N8: 🟡 WATCH
B9: BAJFINANCE | C9: Oversold | D9: 6600 | E9: 7200 | F9: 7600 | G9: 6200 | H9: 12-18 | I9: =IFERROR(ROUND((E9-D9)/(D9-G9),1),0) -> 1.5 | J9: ✅ MED | K9: 100000 | L9: =IFERROR(ROUND((E9-D9)/D9*K9,0),0) -> 9091 | M9: =IFERROR(ROUND((F9-D9)/D9*K9,0),0) -> 15152 | N9: ⚪ SETUP
B10: HDFCBANK | C10: Support Buy | D10: 1500 | E10: 1650 | F10: 1720 | G10: 1440 | H10: 8-12 | I10: =IFERROR(ROUND((E10-D10)/(D10-G10),1),0) -> 2.5 | J10: 🔥 HIGH | K10: 75000 | L10: =IFERROR(ROUND((E10-D10)/D10*K10,0),0) -> 7500 | M10: =IFERROR(ROUND((F10-D10)/D10*K10,0),0) -> 11000 | N10: ⚪ SETUP
B11: SUNPHARMA | C11: Breakout | D11: 920 | E11: 1020 | F11: 1080 | G11: 880 | H11: 7-10 | I11: =IFERROR(ROUND((E11-D11)/(D11-G11),1),0) -> 2.5 | J11: ✅ MED | K11: 45000 | L11: =IFERROR(ROUND((E11-D11)/D11*K11,0),0) -> 4891 | M11: =IFERROR(ROUND((F11-D11)/D11*K11,0),0) -> 7826 | N11: ⚪ SETUP
B13: 📘 SWING TRADING WITH BUYBACK DEEP VALUE — STRATEGY GUIDE
B14: WHY BUYBACK STOCKS? | C14: Company is buying back at higher price = floor support | Management confident in business | Less downside risk
B15: ENTRY TIMING | C15: Enter when stock dips toward buyback accumulation zone | Confirm RSI below 45 | Volume drying up (sellers exhausted)
B16: POSITION SIZING | C16: Never risk more than 2% of total capital per trade | Example: ₹5L portfolio → max ₹10,000 risk per swing trade
B17: STOP LOSS RULE | C17: Always set GTT stop immediately after entry | Stop = 5-7% below entry OR below recent swing low
B18: TARGET SETTING | C18: Target 1 = Previous resistance (take 50% profit) | Target 2 = Next major resistance (trail stop for rest)
B19: HOLDING PERIOD | C19: Swing trades: 5-15 trading days typically | Exit at target even if you think it will go higher
B20: EXIT SIGNALS | C20: Price hits Target 1 = book 50% | RSI crosses above 70 = start exiting | Volume dries up at resistance
B21: AVOID TRAPS | C21: Never swing trade during budget/RBI/election event risk | Avoid stocks with pending court orders/investigations

Sheet 📈 Charts & Analysis
B1: 📈 PORTFOLIO CHARTS & VISUAL ANALYSIS
B2: SECTOR ALLOCATION DATA (auto-linked to portfolio) | I2: MONTHLY P&L TREND (Enter manually)
B3: Sector | C3: Invested (₹) | D3: Current Value (₹) | E3: P&L (₹) | F3: % of Portfolio | I3: Month | J3: P&L (₹)
B4: IT | C4: 3,50,000 | D4: 4,05,000 | E4: 55,000 | F4: 32% | I4: Jan-25 | J4: 8500
B5: Banking | C5: 1,23,750 | D5: 1,18,500 | E5: -5,250 | F5: 12% | I5: Feb-25 | J5: 12000
B6: Energy | C6: 1,20,000 | D6: 1,26,000 | E6: 6,000 | F6: 10% | I6: Mar-25 | J6: -3200
B7: Pharma | C7: 72,000 | D7: 74,000 | E7: 2,000 | F7: 7% | I7: Apr-25 | J7: 15000
B8: Infra | C8: 96,000 | D8: 1,04,000 | E8: 8,000 | F8: 10% | I8: May-25 | J8: 9800
B9: Utilities | C9: 72,000 | D9: 78,000 | E9: 6,000 | F9: 8% | I9: Jun-25 | J9: 18000
B10: Mining | C10: 36,750 | D10: 38,000 | E10: 1,250 | F10: 4% | I10: Jul-25 | J10: -5000
B11: NBFC | C11: 2,04,000 | D11: 2,20,000 | E11: 16,000 | F11: 17% | I11: Aug-25 | J11: 22000
I12: Sep-25 | J12: 14000
I13: Oct-25 | J13: 19000
I14: Nov-25 | J14: 7500
I15: Dec-25 | J15: 25000
B32: 🔔 PORTFOLIO RISK SCORECARD
B33: Risk Factor | C33: Your Score | D33: Benchmark | E33: Status | F33: Comment
B34: Diversification | C34: 8/10 | D34: 7/10 | E34: ✅ GOOD | F34: Spread across 8+ sectors
B35: Stop Loss Coverage | C35: 6/10 | D35: 9/10 | E35: ⚠️ LOW | F35: Set GTT for all open positions
B36: Leverage/Margin | C36: 10/10 | D36: 10/10 | E36: ✅ GOOD | F36: No margin — cash delivery only
B37: Concentration Risk | C37: 7/10 | D37: 8/10 | E37: ⚠️ MEDIUM | F37: IT sector slightly over-weighted
B38: Cash Reserve | C38: 5/10 | D38: 8/10 | E38: 🔴 LOW | F38: Keep 15-20% cash for opportunities
B39: Overall Risk Score | C39: 7.2/10 | D39: 8.4/10 | E39: ⚠️ MEDIUM | F39: Review stop losses and cash

Sheet 📝 Watchlist & Notes
B1: 📝 WATCHLIST, RESEARCH NOTES & LEARNING TRACKER
B2: 👁 WATCHLIST — STOCKS TO BUY ON NEXT DIP
B3: Company | C3: Sector | D3: CMP | E3: Target Entry | F3: Watch Reason | G3: Priority | H3: Research Date | I3: Notes
B4: MARUTI SUZUKI | C4: Auto | D4: 11500 | E4: 10800-11000 | F4: EV transition + strong volumes | G4: HIGH
B5: ASIAN PAINTS | C5: Consumer | D5: 2600 | E5: 2400-2500 | F5: Volume recovery expected Q4 | G5: HIGH
B6: DIVI'S LAB | C6: Pharma | D6: 4800 | E6: 4500-4700 | F6: API export growth story | G6: MEDIUM
B7: PIDILITE | C7: Consumer | D7: 2900 | E7: 2700-2800 | F7: Rural demand recovery | G7: MEDIUM
B8: HDFC LIFE | C8: Insurance | D8: 680 | E8: 640-660 | F8: Insurance penetration growing | G8: HIGH
B9: ZOMATO | C9: Tech | D9: 220 | E9: 190-210 | F9: Food delivery market leader | G9: LOW
B10: ADANIPORTS | C10: Infra | D10: 1350 | E10: 1250-1300 | F10: Cargo volume growth | G10: MEDIUM
B11: MUTHOOT FIN | C11: NBFC | D11: 1900 | E11: 1750-1850 | F11: Gold loan demand rising | G11: LOW
B14: 📜 MY PERSONAL TRADING RULES (Customize These)
B15: 1. NEVER invest more than 10% of portfolio in a single stock
B16: 2. ALWAYS set stop loss / GTT within 24 hours of buying
B17: 3. Buy in 2-3 tranches — never go all-in at once
B18: 4. Minimum 1:2 Risk:Reward ratio for every trade
B19: 5. Book 50% profit when first target is hit, no matter what
B20: 6. No averaging down if fundamental story has changed
B21: 7. Keep 15-20% cash always — opportunity fund
B22: 8. Review portfolio every Sunday evening
B23: 9. Don't trade on tips — only trade what you understand
B24: 10. Log every trade here — review monthly to improve
B26: 📒 TRADE JOURNAL — LOG EVERY TRADE
B27: Date | C27: Stock | D27: Buy Price | E27: Sell Price | F27: Qty | G27: P&L (₹) | H27: % Return | I27: Lesson Learned
G28: =IF(D28=0,"",ROUND((D28-C28)*E28,2)) | H28: =IF(C28=0,"",ROUND((D28-C28)/C28*100,2))
G29: =IF(D29=0,"",ROUND((D29-C29)*E29,2)) | H29: =IF(C29=0,"",ROUND((D29-C29)/C29*100,2))
G30: =IF(D30=0,"",ROUND((D30-C30)*E30,2)) | H30: =IF(C30=0,"",ROUND((D30-C30)/C30*100,2))
G31: =IF(D31=0,"",ROUND((D31-C31)*E31,2)) | H31: =IF(C31=0,"",ROUND((D31-C31)/C31*100,2))
G32: =IF(D32=0,"",ROUND((D32-C32)*E32,2)) | H32: =IF(C32=0,"",ROUND((D32-C32)/C32*100,2))
G33: =IF(D33=0,"",ROUND((D33-C33)*E33,2)) | H33: =IF(C33=0,"",ROUND((D33-C33)/C33*100,2))
G34: =IF(D34=0,"",ROUND((D34-C34)*E34,2)) | H34: =IF(C34=0,"",ROUND((D34-C34)/C34*100,2))
G35: =IF(D35=0,"",ROUND((D35-C35)*E35,2)) | H35: =IF(C35=0,"",ROUND((D35-C35)/C35*100,2))
G36: =IF(D36=0,"",ROUND((D36-C36)*E36,2)) | H36: =IF(C36=0,"",ROUND((D36-C36)/C36*100,2))
G37: =IF(D37=0,"",ROUND((D37-C37)*E37,2)) | H37: =IF(C37=0,"",ROUND((D37-C37)/C37*100,2))
